LICENSE
MANIFEST.in
README.rst
setup.py
dripfeed/__init__.py
dripfeed/comics.py
dripfeed/rss.py
dripfeed/twothree.py
dripfeed.egg-info/PKG-INFO
dripfeed.egg-info/SOURCES.txt
dripfeed.egg-info/dependency_links.txt
dripfeed.egg-info/entry_points.txt
dripfeed.egg-info/not-zip-safe
dripfeed.egg-info/requires.txt
dripfeed.egg-info/top_level.txt