Metadata-Version: 1.1
Name: dripfeed
Version: 1.0.1
Summary: Create an RSS feed of a webcomic archive, for slow perusal.
Home-page: https://bitbucket.org/tikitu/dripfeed
Author: Tikitu de Jager
Author-email: tikitu@logophile.org
License: Copyright 2014 Tikitu de Jager
